strapping/__init__.py
strapping/utils.py
strapping/bootstrap/__init__.py
strapping/bootstrap/sample.py
strapping/stats/__init__.py
strapping/stats/ci.py
strapping/stats/std.py
strapping-0.1.5.dist-info/LICENSE
strapping-0.1.5.dist-info/METADATA
strapping-0.1.5.dist-info/WHEEL
strapping-0.1.5.dist-info/top_level.txt
strapping-0.1.5.dist-info/RECORD
