Metadata-Version: 2.1
Name: strapping
Version: 0.1.5
Summary: A fast implementation of bootstrapping supporting multi-columns data.
Home-page: https://github.com/heolin/strapping
Author: Wojciech Włodarczyk
Author-email: wlodarczyk.woj@example.com
Project-URL: Bug Tracker, https://github.com/heolin/strapping/issues
Classifier: Programming Language :: Python :: 3
Classifier: License :: OSI Approved :: GNU General Public License v3 or later (GPLv3+)
Classifier: Operating System :: OS Independent
Requires-Python: >=3.6
License-File: LICENSE
Requires-Dist: numpy (>=1.20.2)
